<?xml version="1.0" encoding="UTF-8"?>
<itemSettingMapping domain="fw.domain.slip.slipsearchbybuyer.SlipSearchByBuyerList">
    <area id="body" voucherType="21">
        <!-- 伝票番号--> 
        <item isSort="true" > 
            <columnName>V_SLIP_BUY.SLIP_NO</columnName>
            <property>
                <key>property</key>
                <value>slipSearchByBuyerList[N].slipNo</value>
            </property>
        </item> 

        <!-- 購入依頼番号--> 
        <item isSort="true" > 
            <columnName>V_SLIP_BUY.PUR_REQ_NO</columnName>
            <property>
                <key>property</key>
                <value>slipSearchByBuyerList[N].purReqNo</value>
            </property>
        </item> 

        <!-- 依頼区分--> 
        <item isSort="true" > 
            <columnName>V_SLIP_BUY.REQ_TYPE_IND</columnName>
            <property>
                <key>property</key>
                <value>slipSearchByBuyerList[N].reqInd</value>
            </property>
        </item> 

        <!-- 状態--> 
        <!-- <item isSort="true" > 
            <columnName>V_SLIP_BUY.REQ_TYPE_IND</columnName>
            <property>
                <key>property</key>
                <value>slipSearchByBuyerList[N].status</value>
            </property>
        </item> 
        -->
        
        <!-- 購入依頼日--> 
        <item isSort="true" > 
            <columnName>V_SLIP_BUY.PUR_REQ_DATE</columnName>
            <property>
                <key>property</key>
                <value>slipSearchByBuyerList[N].purReqDate.dateOfymdFormat</value>
            </property>
        </item>  

        <!-- 注文番号--> 
        <item isSort="true" > 
            <columnName>V_SLIP_BUY.ORDER_NO</columnName>
            <property>
                <key>property</key>
                <value>slipSearchByBuyerList[N].orderNo</value>
            </property>
        </item> 
        
        <!-- 状態--> 
        <item isSort="true" > 
            <columnName>V_SLIP_BUY.SLIP_STATUS</columnName>
            <property>
                <key>property</key>
                <value>slipSearchByBuyerList[N].slipStatusName</value>
            </property>
        </item> 

        <!-- 注文日--> 
        <item isSort="true" > 
            <columnName>V_SLIP_BUY.ORDER_DATE</columnName>
            <property>
                <key>property</key>
                <value>slipSearchByBuyerList[N].orderDate.dateOfymdFormat</value>
            </property>
        </item> 

        <!-- 見積依頼番号--> 
        <item isSort="true" > 
            <columnName>V_SLIP_BUY.QUOT_REQ_NO</columnName>
            <property>
                <key>property</key>
                <value>slipSearchByBuyerList[N].quotReqNo</value>
            </property>
        </item> 

        <!-- 購入申請番号--> 
        <item isSort="true" > 
            <columnName>V_SLIP_BUY.PUR_APL_NO</columnName>
            <property>
                <key>property</key>
                <value>slipSearchByBuyerList[N].purAplNo</value>
            </property>
        </item> 

        <!-- コメント -->
        <item isSort="false" > 
            <columnName>V_SLIP_BUY.COMMENT_1</columnName>
            <property>
                <key>property</key>
                <value>slipSearchByBuyerList[N].comment1</value>
            </property>
        </item> 
        <!-- 添付 -->
        <!-- ＩＴ２-01429-000 2013/04/03 ADD SBO_CHENCHENG START -->
        <item isSort="false" > 
            <columnName>V_SLIP_BUY.ATTACH_FILE_1</columnName>
            <property>
                <key>property</key>
                <value>slipSearchByBuyerList[N].attachDisp</value>
            </property>
        </item> 
        <!-- ＩＴ２-01429-000 2013/04/03 ADD SBO_CHENCHENG -END- -->
        
        <!-- 件名--> 
        <item isSort="true" > 
            <columnName>V_SLIP_BUY.TITLE_NAME</columnName>
            <property>
                <key>property</key>
                <value>slipSearchByBuyerList[N].titleName</value>
            </property>
        </item> 

        <!-- 取引先コード--> 
        <item isSort="true" > 
            <columnName>V_SLIP_BUY.SUP_CD</columnName>
            <property>
                <key>property</key>
                <value>slipSearchByBuyerList[N].supCd</value>
            </property>
        </item> 

        <!-- 取引先名--> 
        <item isSort="true" > 
            <columnName>V_SLIP_BUY.SUP_ABBR_NAME</columnName>
            <property>
                <key>property</key>
                <value>slipSearchByBuyerList[N].supName</value>
            </property>
        </item> 

        <!-- 下請事業者--> 
        <item isSort="true" > 
            <columnName>V_SLIP_BUY.SUBCON_IND</columnName>
            <property>
                <key>property</key>
                <value>slipSearchByBuyerList[N].subconInd</value>
            </property>
        </item> 

        <!-- EDI--> 
        <item isSort="true" > 
            <columnName>V_SLIP_BUY.EDI_IND</columnName>
            <property>
                <key>property</key>
                <value>slipSearchByBuyerList[N].ediInd</value>
            </property>
        </item> 

        <!-- 品名コード--> 
        <item isSort="true" > 
            <columnName>V_SLIP_BUY.ITEM_CD</columnName>
            <property>
                <key>property</key>
                <value>slipSearchByBuyerList[N].itemCd</value>
            </property>
        </item> 

        <!-- 品名--> 
        <item isSort="true" > 
            <columnName>V_SLIP_BUY.ITEM_NAME</columnName>
            <property>
                <key>property</key>
                <value>slipSearchByBuyerList[N].itemName</value>
            </property>
        </item> 

        <!-- 型式--> 
        <item isSort="true" > 
            <columnName>V_SLIP_BUY.KATASHIKI</columnName>
            <property>
                <key>property</key>
                <value>slipSearchByBuyerList[N].katashiki</value>
            </property>
        </item> 

        <!-- メーカーコード--> 
        <item isSort="true" > 
            <columnName>V_SLIP_BUY.MANUFACT_CD</columnName>
            <property>
                <key>property</key>
                <value>slipSearchByBuyerList[N].manufactCd</value>
            </property>
        </item> 

        <!-- メーカー名--> 
        <item isSort="true" > 
            <columnName>V_SLIP_BUY.MANUFACT_NAME</columnName>
            <property>
                <key>property</key>
                <value>slipSearchByBuyerList[N].manufactName</value>
            </property>
        </item> 

        <!-- 希望納期--> 
        <item isSort="true" > 
            <columnName>V_SLIP_BUY.REQ_DELIV_DATE</columnName>
            <property>
                <key>property</key>
                <value>slipSearchByBuyerList[N].reqDelivDate.dateOfymdFormat</value>
            </property>
        </item> 

        <!-- 注文納期--> 
        <item isSort="true" > 
            <columnName>V_SLIP_BUY.ORDER_DELIV_DATE</columnName>
            <property>
                <key>property</key>
                <value>slipSearchByBuyerList[N].orderDelivDate.dateOfymdFormat</value>
            </property>
        </item> 

        <!-- 希望通貨コード--> 
        <item isSort="true" > 
            <columnName>V_SLIP_BUY.HOPE_CURRENCY_CD</columnName>
            <property>
                <key>property</key>
                <value>slipSearchByBuyerList[N].hopeAmountCurrencyCd</value>
            </property>
        </item> 

        <!-- 通貨コード--> 
        <item isSort="true" > 
            <columnName>V_SLIP_BUY.CURRENCY_CD</columnName>
            <property>
                <key>property</key>
                <value>slipSearchByBuyerList[N].currencyCd</value>
            </property>
        </item> 

        <!-- 希望数量--> 
        <item isSort="true" > 
            <columnName>V_SLIP_BUY.REQ_VOL</columnName>
            <property>
                <key>property</key>
                <value>slipSearchByBuyerList[N].hopeVol.volFormat</value>
            </property>
        </item> 
        
        <!-- 2013/03/22 DEL DAIKO_TAKEDA
        <item>
        -->
        <!-- 2013/03/22 ADD DAIKO_TAKEDA -->
        <item isSort="false">
            <columnName>V_SLIP_BUY.ORDER_VOL</columnName>
            <property>
                <key>property</key>
                <!-- 2013/03/22 DEL DAIKO_TAKEDA
                <value>slipSearchByBuyerList[N].orderVol.volFormat</value>
                -->
                <!-- 2013/03/22 ADD DAIKO_TAKEDA -->
                <value>slipSearchByBuyerList[N].originVol.volFormat</value>
            </property>
        </item>
        
        <item>
            <columnName>V_SLIP_BUY.UNIT_NAME</columnName><!-- 単位 -->
            <property>
                <key>property</key>
                <value>slipSearchByBuyerList[N].unitName</value>
            </property>
        </item>
        
        <item isSort="false">
            <columnName>DUMMY.RCV_REMAIN_AMOUNT</columnName><!-- 受入残数量 -->
            <property>
                <key>property</key>
                <value>slipSearchByBuyerList[N].receiveRemainingVol.volFormat</value>
            </property>
        </item>
        
        <!-- 受入数量 -->
        <item isSort="false">
            <columnName>V_SLIP_BUY.RECEIVED_VOL</columnName>
            <property>
                <key>property</key>
                <value>slipSearchByBuyerList[N].receivedVol.volFormat</value>
            </property>
        </item>
        
        <!-- 2013/03/22 ADD DAIKO_TAKEDA START -->
        <item isSort="false">
            <columnName>V_SLIP_BUY.ORDER_CANCEL_VOL</columnName>
            <property>
                <key>property</key>
                <value>slipSearchByBuyerList[N].orderCancel.orderCancelVol.volFormat</value>
            </property>
        </item>
        <!-- 2013/03/22 ADD DAIKO_TAKEDA -END- -->
        <!-- 検収数量 -->
        <item isSort="false" > 
            <columnName>V_SLIP_BUY.ACCEPT_VOL</columnName>
            <property>
                <key>property</key>
                <value>slipSearchByBuyerList[N].acceptVol.volFormat</value>
            </property>
        </item>
        
        <!-- 単価区分--> 
        <item isSort="true" > 
            <columnName>V_SLIP_BUY.UNIT_PRICE_IND</columnName>
            <property>
                <key>property</key>
                <value>slipSearchByBuyerList[N].unitPriceInd</value>
            </property>
        </item> 

        <!-- 希望通貨コード--> 
        <item isSort="true" > 
            <columnName>V_SLIP_BUY.HOPE_CURRENCY_CD</columnName>
            <property>
                <key>property</key>
                <value>slipSearchByBuyerList[N].hopeAmountCurrencyCd</value>
            </property>
        </item> 

        <!-- 通貨コード--> 
        <item isSort="true" > 
            <columnName>V_SLIP_BUY.CURRENCY_CD</columnName>
            <property>
                <key>property</key>
                <value>slipSearchByBuyerList[N].currencyCd</value>
            </property>
        </item> 

        <!-- 希望単価--> 
        <item isSort="true" > 
            <columnName>V_SLIP_BUY.REQ_UNIT_PRICE</columnName>
            <property>
                <key>property</key>
                <value>slipSearchByBuyerList[N].hopeUnitPrice.amountFormat</value>
            </property>
            <property>
                <key>currencyMark</key>
                <value>slipSearchByBuyerList[N].hopeAmountCurrencyMark</value>
            </property>
        </item> 

        <!-- 希望金額--> 
        <item isSort="true" > 
            <columnName>V_SLIP_BUY.REQ_AMOUNT</columnName>
            <property>
                <key>property</key>
                <value>slipSearchByBuyerList[N].hopeAmount.amountFormat</value>
            </property>
            <property>
                <key>currencyMark</key>
                <!-- ＩＴ３-00402-000 20130801 SBO_SOKOU START -->
                <value>slipSearchByBuyerList[N].hopeAmountCurrencyMark</value>
                <!-- ＩＴ３-00402-000 20130801 SBO_SOKOU END -->
            </property>
        </item> 

        <!-- 注文単価--> 
        <item isSort="true" > 
            <columnName>V_SLIP_BUY.ORDER_UNIT_PRICE</columnName>
            <property>
                <key>property</key>
                <value>slipSearchByBuyerList[N].orderUnitPrice.amountFormat</value>
            </property>
            <property>
                <key>currencyMark</key>
                <value>slipSearchByBuyerList[N].currencyMark</value>
            </property>
        </item> 

        <!-- 注文金額--> 
        <!-- 2013/03/22 DEL DAIKO_TAKEDA
        <item isSort="true" > 
        -->
        <!-- 2013/03/22 ADD DAIKO_TAKEDA -->
        <item isSort="false">
            <columnName>V_SLIP_BUY.ORDER_AMOUNT</columnName>
            <property>
                <key>property</key>
                <!-- 2013/03/22 DEL DAIKO_TAKEDA
                <value>slipSearchByBuyerList[N].orderAmount.amountFormat</value>
                -->
                <!-- 2013/03/22 ADD DAIKO_TAKEDA -->
                <value>slipSearchByBuyerList[N].originAmount.amountFormat</value>
            </property>
            <property>
                <key>currencyMark</key>
                <value>slipSearchByBuyerList[N].currencyMark</value>
            </property>
        </item> 
        <!-- 検収金額 -->
        <item isSort="false" > 
            <columnName>V_SLIP_BUY.ACCEPT_AMOUNT</columnName>
            <property>
                <key>property</key>
                <value>slipSearchByBuyerList[N].acceptAmount.amountFormat</value>
            </property>
            <property>
                <key>currencyMark</key>
                <value>slipSearchByBuyerList[N].currencyMark</value>
            </property>
        </item>
         
        <!-- 2013/03/22 ADD DAIKO_TAKEDA START -->
        <item isSort="false">
            <columnName>V_SLIP_BUY.ORDER_CANCEL_AMOUNT</columnName>
            <property>
                <key>property</key>
                <value>slipSearchByBuyerList[N].orderCancel.orderCancelAmount.amountFormat</value>
            </property>
            <property>
                <key>currencyMark</key>
                <value>slipSearchByBuyerList[N].currencyMark</value>
            </property>
        </item> 
        <!-- 2013/03/22 ADD DAIKO_TAKEDA -END- -->
        
        <!-- 課税区分--> 
        <item isSort="true" > 
            <columnName>V_SLIP_BUY.TAX_IND</columnName>
            <property>
                <key>property</key>
                <value>slipSearchByBuyerList[N].taxInd</value>
            </property>
        </item> 

        <!-- 予算番号--> 
        <item isSort="true" > 
            <columnName>V_SLIP_BUY.BUDGET_NO</columnName>
            <property>
                <key>property</key>
                <value>slipSearchByBuyerList[N].budgetNo</value>
            </property>
        </item> 

        <!-- 科目コード--> 
        <item isSort="true" > 
            <columnName>V_SLIP_BUY.SUBJECT_CD</columnName>
            <property>
                <key>property</key>
                <value>slipSearchByBuyerList[N].subjectCd</value>
            </property>
        </item> 

        <!-- 科目名--> 
        <item isSort="true" > 
            <columnName>V_SLIP_BUY.SUBJECT_NAME</columnName>
            <property>
                <key>property</key>
                <value>slipSearchByBuyerList[N].subjectName</value>
            </property>
        </item> 

        <!-- 納入先コード--> 
        <item isSort="true" > 
            <columnName>V_SLIP_BUY.DELIV_PLACE_CD</columnName>
            <property>
                <key>property</key>
                <value>slipSearchByBuyerList[N].delivPlaceCd</value>
            </property>
        </item> 
        
        <!-- 納入先名--> 
        <item isSort="true" > 
            <columnName>V_SLIP_BUY.DELIV_PLACE_NAME</columnName>
            <property>
                <key>property</key>
                <value>slipSearchByBuyerList[N].delivPlaceName</value>
            </property>
        </item> 
        
        <!-- 訂正区分--> 
        <item isSort="true" > 
            <columnName>V_SLIP_BUY.CORRECT_CD</columnName>
            <property>
                <key>property</key>
                <value>slipSearchByBuyerList[N].correctCd</value>
            </property>
        </item> 

        <!-- 大分類--> 
        <item isSort="true" > 
            <columnName>V_SLIP_BUY.ITEM_CLASS_L_NAME</columnName>
            <property>
                <key>property</key>
                <value>slipSearchByBuyerList[N].itemClassLName</value>
            </property>
        </item> 

        <!-- 中分類--> 
        <item isSort="true" > 
            <columnName>V_SLIP_BUY.ITEM_CLASS_M_NAME</columnName>
            <property>
                <key>property</key>
                <value>slipSearchByBuyerList[N].itemClassMName</value>
            </property>
        </item> 

        <!-- 小分類--> 
        <item isSort="true" > 
            <columnName>V_SLIP_BUY.ITEM_CLASS_S_NAME</columnName>
            <property>
                <key>property</key>
                <value>slipSearchByBuyerList[N].itemClassSName</value>
            </property>
        </item> 

        <!-- 購入依頼部門コード--> 
        <item isSort="true" > 
            <columnName>V_SLIP_BUY.REQ_SECTION_CD</columnName>
            <property>
                <key>property</key>
                <value>slipSearchByBuyerList[N].purReqSectionCd</value>
            </property>
        </item> 

        <!-- 購入依頼部門名--> 
        <item isSort="true" > 
            <columnName>V_SLIP_BUY.REQ_SECTION_NAME</columnName>
            <property>
                <key>property</key>
                <value>slipSearchByBuyerList[N].purReqSectionName</value>
            </property>
        </item> 

        <!-- 購入依頼者コード--> 
        <item isSort="true" > 
            <columnName>V_SLIP_BUY.REQ_USER_ID</columnName>
            <property>
                <key>property</key>
                <value>slipSearchByBuyerList[N].purReqUserCd</value>
            </property>
        </item> 

        <!-- 購入依頼者名--> 
        <item isSort="true" > 
            <columnName>V_SLIP_BUY.REQ_USER_NAME</columnName>
            <property>
                <key>property</key>
                <value>slipSearchByBuyerList[N].purReqUserName</value>
            </property>
        </item> 

        <!-- 購買部門名 --> 
        <item isSort="true" > 
            <columnName>V_SLIP_BUY.BUYER_SECTION_NAME</columnName>
            <property>
                <key>property</key>
                <value>slipSearchByBuyerList[N].buyerSectionName</value>
            </property>
        </item> 

        <!-- 購買部門コード--> 
        <item isSort="true" > 
            <columnName>V_SLIP_BUY.BUYER_SECTION_CD</columnName>
            <property>
                <key>property</key>
                <value>slipSearchByBuyerList[N].buyerSectionCd</value>
            </property>
        </item> 

        <!-- 購買担当者名 --> 
        <item isSort="true" > 
            <columnName>V_SLIP_BUY.BUYER_USER_NAME</columnName>
            <property>
                <key>property</key>
                <value>slipSearchByBuyerList[N].buyerUserName</value>
            </property>
        </item> 

        <!-- 購買担当者ID--> 
        <item isSort="true" > 
            <columnName>V_SLIP_BUY.BUYER_USER_ID</columnName>
            <property>
                <key>property</key>
                <value>slipSearchByBuyerList[N].buyerUserId</value>
            </property>
        </item> 

        <!-- 負担部門コード--> 
        <item isSort="true" > 
            <columnName>V_SLIP_BUY.LOAD_SECTION_CD</columnName>
            <property>
                <key>property</key>
                <value>slipSearchByBuyerList[N].loadSectionCd</value>
            </property>
        </item> 

        <!-- 負担部門名--> 
        <item isSort="true" > 
            <columnName>V_SLIP_BUY.LOAD_SECTION_NAME</columnName>
            <property>
                <key>property</key>
                <value>slipSearchByBuyerList[N].loadSectionName</value>
            </property>
        </item> 

        <!-- 伝票ステータス--> 
        <item isSort="true" > 
            <columnName>V_SLIP_BUY.SLIP_STATUS</columnName>
            <property>
                <key>property</key>
                <value>slipSearchByBuyerList[N].slipStatusName</value>
            </property>
        </item> 

        <!-- 受入状態区分--> 
        <item isSort="true" > 
            <columnName>V_SLIP_BUY.RECEIVE_STATUS_IND</columnName>
            <property>
                <key>property</key>
                <value>slipSearchByBuyerList[N].receiveStatusInd</value>
            </property>
        </item> 

        <!-- 検査状態区分--> 
        <item isSort="true" > 
            <columnName>V_SLIP_BUY.INSPECT_STATUS_IND</columnName>
            <property>
                <key>property</key>
                <value>slipSearchByBuyerList[N].inspectStatusInd</value>
            </property>
        </item> 

        <!-- 検収状態区分--> 
        <item isSort="true" > 
            <columnName>V_SLIP_BUY.ACCEPTANCE_STATUS_IND</columnName>
            <property>
                <key>property</key>
                <value>slipSearchByBuyerList[N].acceptanceStatusInd</value>
            </property>
        </item> 

        <!-- 受入管理情報.納入数量--> 
        <item isSort="true" > 
            <columnName>T_RECEIVE_MNG.APP_ACCEPTANCE_SEQUS</columnName>
            <property>
                <key>property</key>
                <value>slipSearchByBuyerList[N].appAcceptanceSequs</value>
            </property>
        </item> 

        <!-- 見積取得申請.見積取得申請ステータス--> 
        <item isSort="true" > 
            <columnName>T_QUOT_ACQ_APL.QUOT_ACQ_APL_STAT</columnName>
            <property>
                <key>property</key>
                <value>slipSearchByBuyerList[N].quotAcqAplStat</value>
            </property>
        </item> 

        <!-- 見積依頼.見積依頼シーケンス番号--> 
        <item isSort="true" > 
            <columnName>T_QUOT_REQUEST.QUOT_REQ_SEQ</columnName>
            <property>
                <key>property</key>
                <value>slipSearchByBuyerList[N].quotReqSeqNo</value>
            </property>
        </item> 

        <!-- 納期回答情報.件数--> 
        <item isSort="true" > 
            <columnName>TEST1.KENSHU</columnName>
            <property>
                <key>property</key>
                <value>slipSearchByBuyerList[N].kenshu</value>
            </property>
        </item> 

        <!-- 注文.注文シーケンス番号--> 
        <item isSort="true" > 
            <columnName>T_ORDER.ORDER_SEQ</columnName>
            <property>
                <key>property</key>
                <value>slipSearchByBuyerList[N].orderSeq</value>
            </property>
        </item> 

        <!-- 注文.注文番号--> 
        <item isSort="true" > 
            <columnName>T_ORDER.ORDER_NO</columnName>
            <property>
                <key>property</key>
                <value>slipSearchByBuyerList[N].orderNo</value>
            </property>
        </item> 

        <!-- 購入申請シーケンス番号--> 
        <item isSort="true" > 
            <columnName>V_SLIP_BUY.PUR_APL_SEQ</columnName>
            <property>
                <key>property</key>
                <value>slipSearchByBuyerList[N].purAplSeq</value>
            </property>
        </item> 

        <!-- 承認単位番号--> 
        <item isSort="true" > 
            <columnName>V_SLIP_BUY.APP_UNIT_NO</columnName>
            <property>
                <key>property</key>
                <value>slipSearchByBuyerList[N].appUnitNo</value>
            </property>
        </item>
        
        <!-- 購入申請 -->
        <item isSort="false">
            <columnName>T_PUR_APL.EXT_TXT_1</columnName>
            <property>
                <key>property</key>
                <value>slipSearchByBuyerList[N].purAplExtItem.extendTxt.extendTxt1</value>
            </property>
        </item>
        <item isSort="false">
            <columnName>T_PUR_APL.EXT_TXT_2</columnName>
            <property>
                <key>property</key>
                <value>slipSearchByBuyerList[N].purAplExtItem.extendTxt.extendTxt2</value>
            </property>
        </item>
        <item isSort="false">
            <columnName>T_PUR_APL.EXT_TXT_3</columnName>
            <property>
                <key>property</key>
                <value>slipSearchByBuyerList[N].purAplExtItem.extendTxt.extendTxt3</value>
            </property>
        </item>
        <item isSort="false">
            <columnName>T_PUR_APL.EXT_TXT_4</columnName>
            <property>
                <key>property</key>
                <value>slipSearchByBuyerList[N].purAplExtItem.extendTxt.extendTxt4</value>
            </property>
        </item>
        <item isSort="false">
            <columnName>T_PUR_APL.EXT_TXT_5</columnName>
            <property>
                <key>property</key>
                <value>slipSearchByBuyerList[N].purAplExtItem.extendTxt.extendTxt5</value>
            </property>
        </item>
        <item isSort="false">
            <columnName>T_PUR_APL.EXT_TXT_6</columnName>
            <property>
                <key>property</key>
                <value>slipSearchByBuyerList[N].purAplExtItem.extendTxt.extendTxt6</value>
            </property>
        </item>
        <item isSort="false">
            <columnName>T_PUR_APL.EXT_TXT_7</columnName>
            <property>
                <key>property</key>
                <value>slipSearchByBuyerList[N].purAplExtItem.extendTxt.extendTxt7</value>
            </property>
        </item>
        <item isSort="false">
            <columnName>T_PUR_APL.EXT_TXT_8</columnName>
            <property>
                <key>property</key>
                <value>slipSearchByBuyerList[N].purAplExtItem.extendTxt.extendTxt8</value>
            </property>
        </item>
        <item isSort="false">
            <columnName>T_PUR_APL.EXT_TXT_9</columnName>
            <property>
                <key>property</key>
                <value>slipSearchByBuyerList[N].purAplExtItem.extendTxt.extendTxt9</value>
            </property>
        </item>
        <item isSort="false">
            <columnName>T_PUR_APL.EXT_TXT_10</columnName>
            <property>
                <key>property</key>
                <value>slipSearchByBuyerList[N].purAplExtItem.extendTxt.extendTxt10</value>
            </property>
        </item>
        <item isSort="false">
            <columnName>T_PUR_APL.EXT_AREA_1</columnName>
            <property>
                <key>property</key>
                <value>slipSearchByBuyerList[N].purAplExtItem.extendArea.extendArea1</value>
            </property>
        </item>
        <item isSort="false">
            <columnName>T_PUR_APL.EXT_AREA_2</columnName>
            <property>
                <key>property</key>
                <value>slipSearchByBuyerList[N].purAplExtItem.extendArea.extendArea2</value>
            </property>
        </item>
        <item isSort="false">
            <columnName>T_PUR_APL.EXT_AREA_3</columnName>
            <property>
                <key>property</key>
                <value>slipSearchByBuyerList[N].purAplExtItem.extendArea.extendArea3</value>
            </property>
        </item>
        <item isSort="false">
            <columnName>T_PUR_APL.EXT_AREA_4</columnName>
            <property>
                <key>property</key>
                <value>slipSearchByBuyerList[N].purAplExtItem.extendArea.extendArea4</value>
            </property>
        </item>
        <item isSort="false">
            <columnName>T_PUR_APL.EXT_AREA_5</columnName>
            <property>
                <key>property</key>
                <value>slipSearchByBuyerList[N].purAplExtItem.extendArea.extendArea5</value>
            </property>
        </item>
        <item isSort="false">
            <columnName>T_PUR_APL.EXT_DATE_1</columnName>
            <property>
                <key>property</key>
                <value>slipSearchByBuyerList[N].purAplExtItem.extendDate.extendDate1.dateOfymdFormat</value>
            </property>
        </item>
        <item isSort="false">
            <columnName>T_PUR_APL.EXT_DATE_2</columnName>
            <property>
                <key>property</key>
                <value>slipSearchByBuyerList[N].purAplExtItem.extendDate.extendDate2.dateOfymdFormat</value>
            </property>
        </item>
        <item isSort="false">
            <columnName>T_PUR_APL.EXT_DATE_3</columnName>
            <property>
                <key>property</key>
                <value>slipSearchByBuyerList[N].purAplExtItem.extendDate.extendDate3.dateOfymdFormat</value>
            </property>
        </item>
        <item isSort="false">
            <columnName>T_PUR_APL.EXT_DATE_4</columnName>
            <property>
                <key>property</key>
                <value>slipSearchByBuyerList[N].purAplExtItem.extendDate.extendDate4.dateOfymdFormat</value>
            </property>
        </item>
        <item isSort="false">
            <columnName>T_PUR_APL.EXT_DATE_5</columnName>
            <property>
                <key>property</key>
                <value>slipSearchByBuyerList[N].purAplExtItem.extendDate.extendDate5.dateOfymdFormat</value>
            </property>
        </item>
        <item isSort="false">
            <columnName>T_PUR_APL.EXT_INT_1</columnName>
            <property>
                <key>property</key>
                <value>slipSearchByBuyerList[N].purAplExtItem.extendInt.extendInt1.valueFormat</value>
            </property>
        </item>
        <item isSort="false">
            <columnName>T_PUR_APL.EXT_INT_2</columnName>
            <property>
                <key>property</key>
                <value>slipSearchByBuyerList[N].purAplExtItem.extendInt.extendInt2.valueFormat</value>
            </property>
        </item>
        <item isSort="false">
            <columnName>T_PUR_APL.EXT_INT_3</columnName>
            <property>
                <key>property</key>
                <value>slipSearchByBuyerList[N].purAplExtItem.extendInt.extendInt3.valueFormat</value>
            </property>
        </item>
        <item isSort="false">
            <columnName>T_PUR_APL.EXT_INT_4</columnName>
            <property>
                <key>property</key>
                <value>slipSearchByBuyerList[N].purAplExtItem.extendInt.extendInt4.valueFormat</value>
            </property>
        </item>
        <item isSort="false">
            <columnName>T_PUR_APL.EXT_INT_5</columnName>
            <property>
                <key>property</key>
                <value>slipSearchByBuyerList[N].purAplExtItem.extendInt.extendInt5.valueFormat</value>
            </property>
        </item>
        <item isSort="false">
            <columnName>T_PUR_APL.EXT_INT_6</columnName>
            <property>
                <key>property</key>
                <value>slipSearchByBuyerList[N].purAplExtItem.extendInt.extendInt6.valueFormat</value>
            </property>
        </item>
        <item isSort="false">
            <columnName>T_PUR_APL.EXT_INT_7</columnName>
            <property>
                <key>property</key>
                <value>slipSearchByBuyerList[N].purAplExtItem.extendInt.extendInt7.valueFormat</value>
            </property>
        </item>
        <item isSort="false">
            <columnName>T_PUR_APL.EXT_INT_8</columnName>
            <property>
                <key>property</key>
                <value>slipSearchByBuyerList[N].purAplExtItem.extendInt.extendInt8.valueFormat</value>
            </property>
        </item>
        <item isSort="false">
            <columnName>T_PUR_APL.EXT_INT_9</columnName>
            <property>
                <key>property</key>
                <value>slipSearchByBuyerList[N].purAplExtItem.extendInt.extendInt9.valueFormat</value>
            </property>
        </item>
        <item isSort="false">
            <columnName>T_PUR_APL.EXT_INT_10</columnName>
            <property>
                <key>property</key>
                <value>slipSearchByBuyerList[N].purAplExtItem.extendInt.extendInt10.valueFormat</value>
            </property>
        </item>
        <item isSort="false">
            <columnName>T_PUR_APL.EXT_DEC_1</columnName>
            <property>
                <key>property</key>
                <value>slipSearchByBuyerList[N].purAplExtItem.extendDec.extendDec1.valueFormat</value>
            </property>
        </item>
        <item isSort="false">
            <columnName>T_PUR_APL.EXT_DEC_2</columnName>
            <property>
                <key>property</key>
                <value>slipSearchByBuyerList[N].purAplExtItem.extendDec.extendDec2.valueFormat</value>
            </property>
        </item>
        <item isSort="false">
            <columnName>T_PUR_APL.EXT_DEC_3</columnName>
            <property>
                <key>property</key>
                <value>slipSearchByBuyerList[N].purAplExtItem.extendDec.extendDec3.valueFormat</value>
            </property>
        </item>
        <item isSort="false">
            <columnName>T_PUR_APL.EXT_DEC_4</columnName>
            <property>
                <key>property</key>
                <value>slipSearchByBuyerList[N].purAplExtItem.extendDec.extendDec4.valueFormat</value>
            </property>
        </item>
        <item isSort="false">
            <columnName>T_PUR_APL.EXT_DEC_5</columnName>
            <property>
                <key>property</key>
                <value>slipSearchByBuyerList[N].purAplExtItem.extendDec.extendDec5.valueFormat</value>
            </property>
        </item>
        <item isSort="false">
            <columnName>T_PUR_APL.EXT_SEL_1</columnName>
            <property>
                <key>property</key>
                <value>slipSearchByBuyerList[N].purAplExtItem.extendSel.extendSel1</value>
            </property>
        </item>
        <item isSort="false">
            <columnName>T_PUR_APL.EXT_SEL_2</columnName>
            <property>
                <key>property</key>
                <value>slipSearchByBuyerList[N].purAplExtItem.extendSel.extendSel2</value>
            </property>
        </item>
        <item isSort="false">
            <columnName>T_PUR_APL.EXT_SEL_3</columnName>
            <property>
                <key>property</key>
                <value>slipSearchByBuyerList[N].purAplExtItem.extendSel.extendSel3</value>
            </property>
        </item>
        <item isSort="false">
            <columnName>T_PUR_APL.EXT_SEL_4</columnName>
            <property>
                <key>property</key>
                <value>slipSearchByBuyerList[N].purAplExtItem.extendSel.extendSel4</value>
            </property>
        </item>
        <item isSort="false">
            <columnName>T_PUR_APL.EXT_SEL_5</columnName>
            <property>
                <key>property</key>
                <value>slipSearchByBuyerList[N].purAplExtItem.extendSel.extendSel5</value>
            </property>
        </item>
        <item isSort="false">
            <columnName>T_PUR_APL.EXT_SEL_6</columnName>
            <property>
                <key>property</key>
                <value>slipSearchByBuyerList[N].purAplExtItem.extendSel.extendSel6</value>
            </property>
        </item>
        <item isSort="false">
            <columnName>T_PUR_APL.EXT_SEL_7</columnName>
            <property>
                <key>property</key>
                <value>slipSearchByBuyerList[N].purAplExtItem.extendSel.extendSel7</value>
            </property>
        </item>
        <item isSort="false">
            <columnName>T_PUR_APL.EXT_SEL_8</columnName>
            <property>
                <key>property</key>
                <value>slipSearchByBuyerList[N].purAplExtItem.extendSel.extendSel8</value>
            </property>
        </item>
        <item isSort="false">
            <columnName>T_PUR_APL.EXT_SEL_9</columnName>
            <property>
                <key>property</key>
                <value>slipSearchByBuyerList[N].purAplExtItem.extendSel.extendSel9</value>
            </property>
        </item>
        <item isSort="false">
            <columnName>T_PUR_APL.EXT_SEL_10</columnName>
            <property>
                <key>property</key>
                <value>slipSearchByBuyerList[N].purAplExtItem.extendSel.extendSel10</value>
            </property>
        </item>
        <item isSort="false">
            <columnName>T_PUR_APL.EXT_CHK_1</columnName>
            <property>
                <key>property</key>
                <value>slipSearchByBuyerList[N].purAplExtItem.extendChk.extendChk1</value>
            </property>
        </item>
        <item isSort="false">
            <columnName>T_PUR_APL.EXT_CHK_2</columnName>
            <property>
                <key>property</key>
                <value>slipSearchByBuyerList[N].purAplExtItem.extendChk.extendChk2</value>
            </property>
        </item>
        <item isSort="false">
            <columnName>T_PUR_APL.EXT_CHK_3</columnName>
            <property>
                <key>property</key>
                <value>slipSearchByBuyerList[N].purAplExtItem.extendChk.extendChk3</value>
            </property>
        </item>
        <item isSort="false">
            <columnName>T_PUR_APL.EXT_CHK_4</columnName>
            <property>
                <key>property</key>
                <value>slipSearchByBuyerList[N].purAplExtItem.extendChk.extendChk4</value>
            </property>
        </item>
        <item isSort="false">
            <columnName>T_PUR_APL.EXT_CHK_5</columnName>
            <property>
                <key>property</key>
                <value>slipSearchByBuyerList[N].purAplExtItem.extendChk.extendChk5</value>
            </property>
        </item>
        <item isSort="false">
            <columnName>T_PUR_APL.EXT_FILE_1</columnName>
            <property>
                <key>property</key>
                <value>slipSearchByBuyerList[N].purAplExtItem.extendFile.extendFile1.fileName</value>
            </property>
        </item>
        <item isSort="false">
            <columnName>T_PUR_APL.EXT_FILE_2</columnName>
            <property>
                <key>property</key>
                <value>slipSearchByBuyerList[N].purAplExtItem.extendFile.extendFile2.fileName</value>
            </property>
        </item>
        <item isSort="false">
            <columnName>T_PUR_APL.EXT_FILE_3</columnName>
            <property>
                <key>property</key>
                <value>slipSearchByBuyerList[N].purAplExtItem.extendFile.extendFile3.fileName</value>
            </property>
        </item>
        <item isSort="false">
            <columnName>T_PUR_APL.EXT_FILE_BINARY_1</columnName>
            <property>
                <key>property</key>
                <value>slipSearchByBuyerList[N].purAplExtItem.extendFile.extendFile1.binary</value>
            </property>
        </item>
        <item isSort="false">
            <columnName>T_PUR_APL.EXT_FILE_BINARY_2</columnName>
            <property>
                <key>property</key>
                <value>slipSearchByBuyerList[N].purAplExtItem.extendFile.extendFile2.binary</value>
            </property>
        </item>
        <item isSort="false">
            <columnName>T_PUR_APL.EXT_FILE_BINARY_3</columnName>
            <property>
                <key>property</key>
                <value>slipSearchByBuyerList[N].purAplExtItem.extendFile.extendFile3.binary</value>
            </property>
        </item>
        <item isSort="false">
            <columnName>T_PUR_APL.EXT_MST_1</columnName>
            <property>
                <key>masterCd</key>
                <value>slipSearchByBuyerList[N].purAplExtItem.extendMst.extendMst1.mstKey</value>
            </property>
            <property>
                <key>masterName</key>
                <value>slipSearchByBuyerList[N].purAplExtItem.extendMst.extendMst1.mstName</value>
            </property>
        </item>
        <item isSort="false">
            <columnName>T_PUR_APL.EXT_MST_2</columnName>
            <property>
                <key>masterCd</key>
                <value>slipSearchByBuyerList[N].purAplExtItem.extendMst.extendMst2.mstKey</value>
            </property>
            <property>
                <key>masterName</key>
                <value>slipSearchByBuyerList[N].purAplExtItem.extendMst.extendMst2.mstName</value>
            </property>
        </item>
        <item isSort="false">
            <columnName>T_PUR_APL.EXT_MST_3</columnName>
            <property>
                <key>masterCd</key>
                <value>slipSearchByBuyerList[N].purAplExtItem.extendMst.extendMst3.mstKey</value>
            </property>
            <property>
                <key>masterName</key>
                <value>slipSearchByBuyerList[N].purAplExtItem.extendMst.extendMst3.mstName</value>
            </property>
        </item>
        <item isSort="false">
            <columnName>T_PUR_APL.EXT_MST_4</columnName>
            <property>
                <key>masterCd</key>
                <value>slipSearchByBuyerList[N].purAplExtItem.extendMst.extendMst4.mstKey</value>
            </property>
            <property>
                <key>masterName</key>
                <value>slipSearchByBuyerList[N].purAplExtItem.extendMst.extendMst4.mstName</value>
            </property>
        </item>
        <item isSort="false">
            <columnName>T_PUR_APL.EXT_MST_5</columnName>
            <property>
                <key>masterCd</key>
                <value>slipSearchByBuyerList[N].purAplExtItem.extendMst.extendMst5.mstKey</value>
            </property>
            <property>
                <key>masterName</key>
                <value>slipSearchByBuyerList[N].purAplExtItem.extendMst.extendMst5.mstName</value>
            </property>
        </item>
        <item isSort="false">
            <columnName>T_PUR_APL.EXT_MST_6</columnName>
            <property>
                <key>masterCd</key>
                <value>slipSearchByBuyerList[N].purAplExtItem.extendMst.extendMst6.mstKey</value>
            </property>
            <property>
                <key>masterName</key>
                <value>slipSearchByBuyerList[N].purAplExtItem.extendMst.extendMst6.mstName</value>
            </property>
        </item>
        <item isSort="false">
            <columnName>T_PUR_APL.EXT_MST_7</columnName>
            <property>
                <key>masterCd</key>
                <value>slipSearchByBuyerList[N].purAplExtItem.extendMst.extendMst7.mstKey</value>
            </property>
            <property>
                <key>masterName</key>
                <value>slipSearchByBuyerList[N].purAplExtItem.extendMst.extendMst7.mstName</value>
            </property>
        </item>
        <item isSort="false">
            <columnName>T_PUR_APL.EXT_MST_8</columnName>
            <property>
                <key>masterCd</key>
                <value>slipSearchByBuyerList[N].purAplExtItem.extendMst.extendMst8.mstKey</value>
            </property>
            <property>
                <key>masterName</key>
                <value>slipSearchByBuyerList[N].purAplExtItem.extendMst.extendMst8.mstName</value>
            </property>
        </item>
        
        <!-- 購入依頼 -->
        <item isSort="false">
            <columnName>T_PUR_REQUEST.EXT_TXT_1</columnName>
            <property>
                <key>property</key>
                <value>slipSearchByBuyerList[N].purRequestExtItem.extendTxt.extendTxt1</value>
            </property>
        </item>
        <item isSort="false">
            <columnName>T_PUR_REQUEST.EXT_TXT_2</columnName>
            <property>
                <key>property</key>
                <value>slipSearchByBuyerList[N].purRequestExtItem.extendTxt.extendTxt2</value>
            </property>
        </item>
        <item isSort="false">
            <columnName>T_PUR_REQUEST.EXT_TXT_3</columnName>
            <property>
                <key>property</key>
                <value>slipSearchByBuyerList[N].purRequestExtItem.extendTxt.extendTxt3</value>
            </property>
        </item>
        <item isSort="false">
            <columnName>T_PUR_REQUEST.EXT_TXT_4</columnName>
            <property>
                <key>property</key>
                <value>slipSearchByBuyerList[N].purRequestExtItem.extendTxt.extendTxt4</value>
            </property>
        </item>
        <item isSort="false">
            <columnName>T_PUR_REQUEST.EXT_TXT_5</columnName>
            <property>
                <key>property</key>
                <value>slipSearchByBuyerList[N].purRequestExtItem.extendTxt.extendTxt5</value>
            </property>
        </item>
        <item isSort="false">
            <columnName>T_PUR_REQUEST.EXT_TXT_6</columnName>
            <property>
                <key>property</key>
                <value>slipSearchByBuyerList[N].purRequestExtItem.extendTxt.extendTxt6</value>
            </property>
        </item>
        <item isSort="false">
            <columnName>T_PUR_REQUEST.EXT_TXT_7</columnName>
            <property>
                <key>property</key>
                <value>slipSearchByBuyerList[N].purRequestExtItem.extendTxt.extendTxt7</value>
            </property>
        </item>
        <item isSort="false">
            <columnName>T_PUR_REQUEST.EXT_TXT_8</columnName>
            <property>
                <key>property</key>
                <value>slipSearchByBuyerList[N].purRequestExtItem.extendTxt.extendTxt8</value>
            </property>
        </item>
        <item isSort="false">
            <columnName>T_PUR_REQUEST.EXT_TXT_9</columnName>
            <property>
                <key>property</key>
                <value>slipSearchByBuyerList[N].purRequestExtItem.extendTxt.extendTxt9</value>
            </property>
        </item>
        <item isSort="false">
            <columnName>T_PUR_REQUEST.EXT_TXT_10</columnName>
            <property>
                <key>property</key>
                <value>slipSearchByBuyerList[N].purRequestExtItem.extendTxt.extendTxt10</value>
            </property>
        </item>
        <item isSort="false">
            <columnName>T_PUR_REQUEST.EXT_AREA_1</columnName>
            <property>
                <key>property</key>
                <value>slipSearchByBuyerList[N].purRequestExtItem.extendArea.extendArea1</value>
            </property>
        </item>
        <item isSort="false">
            <columnName>T_PUR_REQUEST.EXT_AREA_2</columnName>
            <property>
                <key>property</key>
                <value>slipSearchByBuyerList[N].purRequestExtItem.extendArea.extendArea2</value>
            </property>
        </item>
        <item isSort="false">
            <columnName>T_PUR_REQUEST.EXT_AREA_3</columnName>
            <property>
                <key>property</key>
                <value>slipSearchByBuyerList[N].purRequestExtItem.extendArea.extendArea3</value>
            </property>
        </item>
        <item isSort="false">
            <columnName>T_PUR_REQUEST.EXT_AREA_4</columnName>
            <property>
                <key>property</key>
                <value>slipSearchByBuyerList[N].purRequestExtItem.extendArea.extendArea4</value>
            </property>
        </item>
        <item isSort="false">
            <columnName>T_PUR_REQUEST.EXT_AREA_5</columnName>
            <property>
                <key>property</key>
                <value>slipSearchByBuyerList[N].purRequestExtItem.extendArea.extendArea5</value>
            </property>
        </item>
        <item isSort="false">
            <columnName>T_PUR_REQUEST.EXT_DATE_1</columnName>
            <property>
                <key>property</key>
                <value>slipSearchByBuyerList[N].purRequestExtItem.extendDate.extendDate1.dateOfymdFormat</value>
            </property>
        </item>
        <item isSort="false">
            <columnName>T_PUR_REQUEST.EXT_DATE_2</columnName>
            <property>
                <key>property</key>
                <value>slipSearchByBuyerList[N].purRequestExtItem.extendDate.extendDate2.dateOfymdFormat</value>
            </property>
        </item>
        <item isSort="false">
            <columnName>T_PUR_REQUEST.EXT_DATE_3</columnName>
            <property>
                <key>property</key>
                <value>slipSearchByBuyerList[N].purRequestExtItem.extendDate.extendDate3.dateOfymdFormat</value>
            </property>
        </item>
        <item isSort="false">
            <columnName>T_PUR_REQUEST.EXT_DATE_4</columnName>
            <property>
                <key>property</key>
                <value>slipSearchByBuyerList[N].purRequestExtItem.extendDate.extendDate4.dateOfymdFormat</value>
            </property>
        </item>
        <item isSort="false">
            <columnName>T_PUR_REQUEST.EXT_DATE_5</columnName>
            <property>
                <key>property</key>
                <value>slipSearchByBuyerList[N].purRequestExtItem.extendDate.extendDate5.dateOfymdFormat</value>
            </property>
        </item>
        <item isSort="false">
            <columnName>T_PUR_REQUEST.EXT_INT_1</columnName>
            <property>
                <key>property</key>
                <value>slipSearchByBuyerList[N].purRequestExtItem.extendInt.extendInt1.valueFormat</value>
            </property>
        </item>
        <item isSort="false">
            <columnName>T_PUR_REQUEST.EXT_INT_2</columnName>
            <property>
                <key>property</key>
                <value>slipSearchByBuyerList[N].purRequestExtItem.extendInt.extendInt2.valueFormat</value>
            </property>
        </item>
        <item isSort="false">
            <columnName>T_PUR_REQUEST.EXT_INT_3</columnName>
            <property>
                <key>property</key>
                <value>slipSearchByBuyerList[N].purRequestExtItem.extendInt.extendInt3.valueFormat</value>
            </property>
        </item>
        <item isSort="false">
            <columnName>T_PUR_REQUEST.EXT_INT_4</columnName>
            <property>
                <key>property</key>
                <value>slipSearchByBuyerList[N].purRequestExtItem.extendInt.extendInt4.valueFormat</value>
            </property>
        </item>
        <item isSort="false">
            <columnName>T_PUR_REQUEST.EXT_INT_5</columnName>
            <property>
                <key>property</key>
                <value>slipSearchByBuyerList[N].purRequestExtItem.extendInt.extendInt5.valueFormat</value>
            </property>
        </item>
        <item isSort="false">
            <columnName>T_PUR_REQUEST.EXT_INT_6</columnName>
            <property>
                <key>property</key>
                <value>slipSearchByBuyerList[N].purRequestExtItem.extendInt.extendInt6.valueFormat</value>
            </property>
        </item>
        <item isSort="false">
            <columnName>T_PUR_REQUEST.EXT_INT_7</columnName>
            <property>
                <key>property</key>
                <value>slipSearchByBuyerList[N].purRequestExtItem.extendInt.extendInt7.valueFormat</value>
            </property>
        </item>
        <item isSort="false">
            <columnName>T_PUR_REQUEST.EXT_INT_8</columnName>
            <property>
                <key>property</key>
                <value>slipSearchByBuyerList[N].purRequestExtItem.extendInt.extendInt8.valueFormat</value>
            </property>
        </item>
        <item isSort="false">
            <columnName>T_PUR_REQUEST.EXT_INT_9</columnName>
            <property>
                <key>property</key>
                <value>slipSearchByBuyerList[N].purRequestExtItem.extendInt.extendInt9.valueFormat</value>
            </property>
        </item>
        <item isSort="false">
            <columnName>T_PUR_REQUEST.EXT_INT_10</columnName>
            <property>
                <key>property</key>
                <value>slipSearchByBuyerList[N].purRequestExtItem.extendInt.extendInt10.valueFormat</value>
            </property>
        </item>
        <item isSort="false">
            <columnName>T_PUR_REQUEST.EXT_DEC_1</columnName>
            <property>
                <key>property</key>
                <value>slipSearchByBuyerList[N].purRequestExtItem.extendDec.extendDec1.valueFormat</value>
            </property>
        </item>
        <item isSort="false">
            <columnName>T_PUR_REQUEST.EXT_DEC_2</columnName>
            <property>
                <key>property</key>
                <value>slipSearchByBuyerList[N].purRequestExtItem.extendDec.extendDec2.valueFormat</value>
            </property>
        </item>
        <item isSort="false">
            <columnName>T_PUR_REQUEST.EXT_DEC_3</columnName>
            <property>
                <key>property</key>
                <value>slipSearchByBuyerList[N].purRequestExtItem.extendDec.extendDec3.valueFormat</value>
            </property>
        </item>
        <item isSort="false">
            <columnName>T_PUR_REQUEST.EXT_DEC_4</columnName>
            <property>
                <key>property</key>
                <value>slipSearchByBuyerList[N].purRequestExtItem.extendDec.extendDec4.valueFormat</value>
            </property>
        </item>
        <item isSort="false">
            <columnName>T_PUR_REQUEST.EXT_DEC_5</columnName>
            <property>
                <key>property</key>
                <value>slipSearchByBuyerList[N].purRequestExtItem.extendDec.extendDec5.valueFormat</value>
            </property>
        </item>
        <item isSort="false">
            <columnName>T_PUR_REQUEST.EXT_SEL_1</columnName>
            <property>
                <key>property</key>
                <value>slipSearchByBuyerList[N].purRequestExtItem.extendSel.extendSel1</value>
            </property>
        </item>
        <item isSort="false">
            <columnName>T_PUR_REQUEST.EXT_SEL_2</columnName>
            <property>
                <key>property</key>
                <value>slipSearchByBuyerList[N].purRequestExtItem.extendSel.extendSel2</value>
            </property>
        </item>
        <item isSort="false">
            <columnName>T_PUR_REQUEST.EXT_SEL_3</columnName>
            <property>
                <key>property</key>
                <value>slipSearchByBuyerList[N].purRequestExtItem.extendSel.extendSel3</value>
            </property>
        </item>
        <item isSort="false">
            <columnName>T_PUR_REQUEST.EXT_SEL_4</columnName>
            <property>
                <key>property</key>
                <value>slipSearchByBuyerList[N].purRequestExtItem.extendSel.extendSel4</value>
            </property>
        </item>
        <item isSort="false">
            <columnName>T_PUR_REQUEST.EXT_SEL_5</columnName>
            <property>
                <key>property</key>
                <value>slipSearchByBuyerList[N].purRequestExtItem.extendSel.extendSel5</value>
            </property>
        </item>
        <item isSort="false">
            <columnName>T_PUR_REQUEST.EXT_SEL_6</columnName>
            <property>
                <key>property</key>
                <value>slipSearchByBuyerList[N].purRequestExtItem.extendSel.extendSel6</value>
            </property>
        </item>
        <item isSort="false">
            <columnName>T_PUR_REQUEST.EXT_SEL_7</columnName>
            <property>
                <key>property</key>
                <value>slipSearchByBuyerList[N].purRequestExtItem.extendSel.extendSel7</value>
            </property>
        </item>
        <item isSort="false">
            <columnName>T_PUR_REQUEST.EXT_SEL_8</columnName>
            <property>
                <key>property</key>
                <value>slipSearchByBuyerList[N].purRequestExtItem.extendSel.extendSel8</value>
            </property>
        </item>
        <item isSort="false">
            <columnName>T_PUR_REQUEST.EXT_SEL_9</columnName>
            <property>
                <key>property</key>
                <value>slipSearchByBuyerList[N].purRequestExtItem.extendSel.extendSel9</value>
            </property>
        </item>
        <item isSort="false">
            <columnName>T_PUR_REQUEST.EXT_SEL_10</columnName>
            <property>
                <key>property</key>
                <value>slipSearchByBuyerList[N].purRequestExtItem.extendSel.extendSel10</value>
            </property>
        </item>
        <item isSort="false">
            <columnName>T_PUR_REQUEST.EXT_CHK_1</columnName>
            <property>
                <key>property</key>
                <value>slipSearchByBuyerList[N].purRequestExtItem.extendChk.extendChk1</value>
            </property>
        </item>
        <item isSort="false">
            <columnName>T_PUR_REQUEST.EXT_CHK_2</columnName>
            <property>
                <key>property</key>
                <value>slipSearchByBuyerList[N].purRequestExtItem.extendChk.extendChk2</value>
            </property>
        </item>
        <item isSort="false">
            <columnName>T_PUR_REQUEST.EXT_CHK_3</columnName>
            <property>
                <key>property</key>
                <value>slipSearchByBuyerList[N].purRequestExtItem.extendChk.extendChk3</value>
            </property>
        </item>
        <item isSort="false">
            <columnName>T_PUR_REQUEST.EXT_CHK_4</columnName>
            <property>
                <key>property</key>
                <value>slipSearchByBuyerList[N].purRequestExtItem.extendChk.extendChk4</value>
            </property>
        </item>
        <item isSort="false">
            <columnName>T_PUR_REQUEST.EXT_CHK_5</columnName>
            <property>
                <key>property</key>
                <value>slipSearchByBuyerList[N].purRequestExtItem.extendChk.extendChk5</value>
            </property>
        </item>
        <item isSort="false">
            <columnName>T_PUR_REQUEST.EXT_FILE_1</columnName>
            <property>
                <key>property</key>
                <value>slipSearchByBuyerList[N].purRequestExtItem.extendFile.extendFile1.fileName</value>
            </property>
        </item>
        <item isSort="false">
            <columnName>T_PUR_REQUEST.EXT_FILE_2</columnName>
            <property>
                <key>property</key>
                <value>slipSearchByBuyerList[N].purRequestExtItem.extendFile.extendFile2.fileName</value>
            </property>
        </item>
        <item isSort="false">
            <columnName>T_PUR_REQUEST.EXT_FILE_3</columnName>
            <property>
                <key>property</key>
                <value>slipSearchByBuyerList[N].purRequestExtItem.extendFile.extendFile3.fileName</value>
            </property>
        </item>
        <item isSort="false">
            <columnName>T_PUR_REQUEST.EXT_FILE_BINARY_1</columnName>
            <property>
                <key>property</key>
                <value>slipSearchByBuyerList[N].purRequestExtItem.extendFile.extendFile1.binary</value>
            </property>
        </item>
        <item isSort="false">
            <columnName>T_PUR_REQUEST.EXT_FILE_BINARY_2</columnName>
            <property>
                <key>property</key>
                <value>slipSearchByBuyerList[N].purRequestExtItem.extendFile.extendFile2.binary</value>
            </property>
        </item>
        <item isSort="false">
            <columnName>T_PUR_REQUEST.EXT_FILE_BINARY_3</columnName>
            <property>
                <key>property</key>
                <value>slipSearchByBuyerList[N].purRequestExtItem.extendFile.extendFile3.binary</value>
            </property>
        </item>
        <item isSort="false">
            <columnName>T_PUR_REQUEST.EXT_MST_1</columnName>
            <property>
                <key>masterCd</key>
                <value>slipSearchByBuyerList[N].purRequestExtItem.extendMst.extendMst1.mstKey</value>
            </property>
            <property>
                <key>masterName</key>
                <value>slipSearchByBuyerList[N].purRequestExtItem.extendMst.extendMst1.mstName</value>
            </property>
        </item>
        <item isSort="false">
            <columnName>T_PUR_REQUEST.EXT_MST_2</columnName>
            <property>
                <key>masterCd</key>
                <value>slipSearchByBuyerList[N].purRequestExtItem.extendMst.extendMst2.mstKey</value>
            </property>
            <property>
                <key>masterName</key>
                <value>slipSearchByBuyerList[N].purRequestExtItem.extendMst.extendMst2.mstName</value>
            </property>
        </item>
        <item isSort="false">
            <columnName>T_PUR_REQUEST.EXT_MST_3</columnName>
            <property>
                <key>masterCd</key>
                <value>slipSearchByBuyerList[N].purRequestExtItem.extendMst.extendMst3.mstKey</value>
            </property>
            <property>
                <key>masterName</key>
                <value>slipSearchByBuyerList[N].purRequestExtItem.extendMst.extendMst3.mstName</value>
            </property>
        </item>
        <item isSort="false">
            <columnName>T_PUR_REQUEST.EXT_MST_4</columnName>
            <property>
                <key>masterCd</key>
                <value>slipSearchByBuyerList[N].purRequestExtItem.extendMst.extendMst4.mstKey</value>
            </property>
            <property>
                <key>masterName</key>
                <value>slipSearchByBuyerList[N].purRequestExtItem.extendMst.extendMst4.mstName</value>
            </property>
        </item>
        <item isSort="false">
            <columnName>T_PUR_REQUEST.EXT_MST_5</columnName>
            <property>
                <key>masterCd</key>
                <value>slipSearchByBuyerList[N].purRequestExtItem.extendMst.extendMst5.mstKey</value>
            </property>
            <property>
                <key>masterName</key>
                <value>slipSearchByBuyerList[N].purRequestExtItem.extendMst.extendMst5.mstName</value>
            </property>
        </item>
        <item isSort="false">
            <columnName>T_PUR_REQUEST.EXT_MST_6</columnName>
            <property>
                <key>masterCd</key>
                <value>slipSearchByBuyerList[N].purRequestExtItem.extendMst.extendMst6.mstKey</value>
            </property>
            <property>
                <key>masterName</key>
                <value>slipSearchByBuyerList[N].purRequestExtItem.extendMst.extendMst6.mstName</value>
            </property>
        </item>
        <item isSort="false">
            <columnName>T_PUR_REQUEST.EXT_MST_7</columnName>
            <property>
                <key>masterCd</key>
                <value>slipSearchByBuyerList[N].purRequestExtItem.extendMst.extendMst7.mstKey</value>
            </property>
            <property>
                <key>masterName</key>
                <value>slipSearchByBuyerList[N].purRequestExtItem.extendMst.extendMst7.mstName</value>
            </property>
        </item>
        <item isSort="false">
            <columnName>T_PUR_REQUEST.EXT_MST_8</columnName>
            <property>
                <key>masterCd</key>
                <value>slipSearchByBuyerList[N].purRequestExtItem.extendMst.extendMst8.mstKey</value>
            </property>
            <property>
                <key>masterName</key>
                <value>slipSearchByBuyerList[N].purRequestExtItem.extendMst.extendMst8.mstName</value>
            </property>
        </item>
        
        <!-- 注文 -->
        <item isSort="false">
            <columnName>T_ORDER.EXT_TXT_1</columnName>
            <property>
                <key>property</key>
                <value>slipSearchByBuyerList[N].orderExtItem.extendTxt.extendTxt1</value>
            </property>
        </item>
        <item isSort="false">
            <columnName>T_ORDER.EXT_TXT_2</columnName>
            <property>
                <key>property</key>
                <value>slipSearchByBuyerList[N].orderExtItem.extendTxt.extendTxt2</value>
            </property>
        </item>
        <item isSort="false">
            <columnName>T_ORDER.EXT_TXT_3</columnName>
            <property>
                <key>property</key>
                <value>slipSearchByBuyerList[N].orderExtItem.extendTxt.extendTxt3</value>
            </property>
        </item>
        <item isSort="false">
            <columnName>T_ORDER.EXT_TXT_4</columnName>
            <property>
                <key>property</key>
                <value>slipSearchByBuyerList[N].orderExtItem.extendTxt.extendTxt4</value>
            </property>
        </item>
        <item isSort="false">
            <columnName>T_ORDER.EXT_TXT_5</columnName>
            <property>
                <key>property</key>
                <value>slipSearchByBuyerList[N].orderExtItem.extendTxt.extendTxt5</value>
            </property>
        </item>
        <item isSort="false">
            <columnName>T_ORDER.EXT_TXT_6</columnName>
            <property>
                <key>property</key>
                <value>slipSearchByBuyerList[N].orderExtItem.extendTxt.extendTxt6</value>
            </property>
        </item>
        <item isSort="false">
            <columnName>T_ORDER.EXT_TXT_7</columnName>
            <property>
                <key>property</key>
                <value>slipSearchByBuyerList[N].orderExtItem.extendTxt.extendTxt7</value>
            </property>
        </item>
        <item isSort="false">
            <columnName>T_ORDER.EXT_TXT_8</columnName>
            <property>
                <key>property</key>
                <value>slipSearchByBuyerList[N].orderExtItem.extendTxt.extendTxt8</value>
            </property>
        </item>
        <item isSort="false">
            <columnName>T_ORDER.EXT_TXT_9</columnName>
            <property>
                <key>property</key>
                <value>slipSearchByBuyerList[N].orderExtItem.extendTxt.extendTxt9</value>
            </property>
        </item>
        <item isSort="false">
            <columnName>T_ORDER.EXT_TXT_10</columnName>
            <property>
                <key>property</key>
                <value>slipSearchByBuyerList[N].orderExtItem.extendTxt.extendTxt10</value>
            </property>
        </item>
        <item isSort="false">
            <columnName>T_ORDER.EXT_AREA_1</columnName>
            <property>
                <key>property</key>
                <value>slipSearchByBuyerList[N].orderExtItem.extendArea.extendArea1</value>
            </property>
        </item>
        <item isSort="false">
            <columnName>T_ORDER.EXT_AREA_2</columnName>
            <property>
                <key>property</key>
                <value>slipSearchByBuyerList[N].orderExtItem.extendArea.extendArea2</value>
            </property>
        </item>
        <item isSort="false">
            <columnName>T_ORDER.EXT_AREA_3</columnName>
            <property>
                <key>property</key>
                <value>slipSearchByBuyerList[N].orderExtItem.extendArea.extendArea3</value>
            </property>
        </item>
        <item isSort="false">
            <columnName>T_ORDER.EXT_AREA_4</columnName>
            <property>
                <key>property</key>
                <value>slipSearchByBuyerList[N].orderExtItem.extendArea.extendArea4</value>
            </property>
        </item>
        <item isSort="false">
            <columnName>T_ORDER.EXT_AREA_5</columnName>
            <property>
                <key>property</key>
                <value>slipSearchByBuyerList[N].orderExtItem.extendArea.extendArea5</value>
            </property>
        </item>
        <item isSort="false">
            <columnName>T_ORDER.EXT_DATE_1</columnName>
            <property>
                <key>property</key>
                <value>slipSearchByBuyerList[N].orderExtItem.extendDate.extendDate1.dateOfymdFormat</value>
            </property>
        </item>
        <item isSort="false">
            <columnName>T_ORDER.EXT_DATE_2</columnName>
            <property>
                <key>property</key>
                <value>slipSearchByBuyerList[N].orderExtItem.extendDate.extendDate2.dateOfymdFormat</value>
            </property>
        </item>
        <item isSort="false">
            <columnName>T_ORDER.EXT_DATE_3</columnName>
            <property>
                <key>property</key>
                <value>slipSearchByBuyerList[N].orderExtItem.extendDate.extendDate3.dateOfymdFormat</value>
            </property>
        </item>
        <item isSort="false">
            <columnName>T_ORDER.EXT_DATE_4</columnName>
            <property>
                <key>property</key>
                <value>slipSearchByBuyerList[N].orderExtItem.extendDate.extendDate4.dateOfymdFormat</value>
            </property>
        </item>
        <item isSort="false">
            <columnName>T_ORDER.EXT_DATE_5</columnName>
            <property>
                <key>property</key>
                <value>slipSearchByBuyerList[N].orderExtItem.extendDate.extendDate5.dateOfymdFormat</value>
            </property>
        </item>
        <item isSort="false">
            <columnName>T_ORDER.EXT_INT_1</columnName>
            <property>
                <key>property</key>
                <value>slipSearchByBuyerList[N].orderExtItem.extendInt.extendInt1.valueFormat</value>
            </property>
        </item>
        <item isSort="false">
            <columnName>T_ORDER.EXT_INT_2</columnName>
            <property>
                <key>property</key>
                <value>slipSearchByBuyerList[N].orderExtItem.extendInt.extendInt2.valueFormat</value>
            </property>
        </item>
        <item isSort="false">
            <columnName>T_ORDER.EXT_INT_3</columnName>
            <property>
                <key>property</key>
                <value>slipSearchByBuyerList[N].orderExtItem.extendInt.extendInt3.valueFormat</value>
            </property>
        </item>
        <item isSort="false">
            <columnName>T_ORDER.EXT_INT_4</columnName>
            <property>
                <key>property</key>
                <value>slipSearchByBuyerList[N].orderExtItem.extendInt.extendInt4.valueFormat</value>
            </property>
        </item>
        <item isSort="false">
            <columnName>T_ORDER.EXT_INT_5</columnName>
            <property>
                <key>property</key>
                <value>slipSearchByBuyerList[N].orderExtItem.extendInt.extendInt5.valueFormat</value>
            </property>
        </item>
        <item isSort="false">
            <columnName>T_ORDER.EXT_INT_6</columnName>
            <property>
                <key>property</key>
                <value>slipSearchByBuyerList[N].orderExtItem.extendInt.extendInt6.valueFormat</value>
            </property>
        </item>
        <item isSort="false">
            <columnName>T_ORDER.EXT_INT_7</columnName>
            <property>
                <key>property</key>
                <value>slipSearchByBuyerList[N].orderExtItem.extendInt.extendInt7.valueFormat</value>
            </property>
        </item>
        <item isSort="false">
            <columnName>T_ORDER.EXT_INT_8</columnName>
            <property>
                <key>property</key>
                <value>slipSearchByBuyerList[N].orderExtItem.extendInt.extendInt8.valueFormat</value>
            </property>
        </item>
        <item isSort="false">
            <columnName>T_ORDER.EXT_INT_9</columnName>
            <property>
                <key>property</key>
                <value>slipSearchByBuyerList[N].orderExtItem.extendInt.extendInt9.valueFormat</value>
            </property>
        </item>
        <item isSort="false">
            <columnName>T_ORDER.EXT_INT_10</columnName>
            <property>
                <key>property</key>
                <value>slipSearchByBuyerList[N].orderExtItem.extendInt.extendInt10.valueFormat</value>
            </property>
        </item>
        <item isSort="false">
            <columnName>T_ORDER.EXT_DEC_1</columnName>
            <property>
                <key>property</key>
                <value>slipSearchByBuyerList[N].orderExtItem.extendDec.extendDec1.valueFormat</value>
            </property>
        </item>
        <item isSort="false">
            <columnName>T_ORDER.EXT_DEC_2</columnName>
            <property>
                <key>property</key>
                <value>slipSearchByBuyerList[N].orderExtItem.extendDec.extendDec2.valueFormat</value>
            </property>
        </item>
        <item isSort="false">
            <columnName>T_ORDER.EXT_DEC_3</columnName>
            <property>
                <key>property</key>
                <value>slipSearchByBuyerList[N].orderExtItem.extendDec.extendDec3.valueFormat</value>
            </property>
        </item>
        <item isSort="false">
            <columnName>T_ORDER.EXT_DEC_4</columnName>
            <property>
                <key>property</key>
                <value>slipSearchByBuyerList[N].orderExtItem.extendDec.extendDec4.valueFormat</value>
            </property>
        </item>
        <item isSort="false">
            <columnName>T_ORDER.EXT_DEC_5</columnName>
            <property>
                <key>property</key>
                <value>slipSearchByBuyerList[N].orderExtItem.extendDec.extendDec5.valueFormat</value>
            </property>
        </item>
        <item isSort="false">
            <columnName>T_ORDER.EXT_SEL_1</columnName>
            <property>
                <key>property</key>
                <value>slipSearchByBuyerList[N].orderExtItem.extendSel.extendSel1</value>
            </property>
        </item>
        <item isSort="false">
            <columnName>T_ORDER.EXT_SEL_2</columnName>
            <property>
                <key>property</key>
                <value>slipSearchByBuyerList[N].orderExtItem.extendSel.extendSel2</value>
            </property>
        </item>
        <item isSort="false">
            <columnName>T_ORDER.EXT_SEL_3</columnName>
            <property>
                <key>property</key>
                <value>slipSearchByBuyerList[N].orderExtItem.extendSel.extendSel3</value>
            </property>
        </item>
        <item isSort="false">
            <columnName>T_ORDER.EXT_SEL_4</columnName>
            <property>
                <key>property</key>
                <value>slipSearchByBuyerList[N].orderExtItem.extendSel.extendSel4</value>
            </property>
        </item>
        <item isSort="false">
            <columnName>T_ORDER.EXT_SEL_5</columnName>
            <property>
                <key>property</key>
                <value>slipSearchByBuyerList[N].orderExtItem.extendSel.extendSel5</value>
            </property>
        </item>
        <item isSort="false">
            <columnName>T_ORDER.EXT_SEL_6</columnName>
            <property>
                <key>property</key>
                <value>slipSearchByBuyerList[N].orderExtItem.extendSel.extendSel6</value>
            </property>
        </item>
        <item isSort="false">
            <columnName>T_ORDER.EXT_SEL_7</columnName>
            <property>
                <key>property</key>
                <value>slipSearchByBuyerList[N].orderExtItem.extendSel.extendSel7</value>
            </property>
        </item>
        <item isSort="false">
            <columnName>T_ORDER.EXT_SEL_8</columnName>
            <property>
                <key>property</key>
                <value>slipSearchByBuyerList[N].orderExtItem.extendSel.extendSel8</value>
            </property>
        </item>
        <item isSort="false">
            <columnName>T_ORDER.EXT_SEL_9</columnName>
            <property>
                <key>property</key>
                <value>slipSearchByBuyerList[N].orderExtItem.extendSel.extendSel9</value>
            </property>
        </item>
        <item isSort="false">
            <columnName>T_ORDER.EXT_SEL_10</columnName>
            <property>
                <key>property</key>
                <value>slipSearchByBuyerList[N].orderExtItem.extendSel.extendSel10</value>
            </property>
        </item>
        <item isSort="false">
            <columnName>T_ORDER.EXT_CHK_1</columnName>
            <property>
                <key>property</key>
                <value>slipSearchByBuyerList[N].orderExtItem.extendChk.extendChk1</value>
            </property>
        </item>
        <item isSort="false">
            <columnName>T_ORDER.EXT_CHK_2</columnName>
            <property>
                <key>property</key>
                <value>slipSearchByBuyerList[N].orderExtItem.extendChk.extendChk2</value>
            </property>
        </item>
        <item isSort="false">
            <columnName>T_ORDER.EXT_CHK_3</columnName>
            <property>
                <key>property</key>
                <value>slipSearchByBuyerList[N].orderExtItem.extendChk.extendChk3</value>
            </property>
        </item>
        <item isSort="false">
            <columnName>T_ORDER.EXT_CHK_4</columnName>
            <property>
                <key>property</key>
                <value>slipSearchByBuyerList[N].orderExtItem.extendChk.extendChk4</value>
            </property>
        </item>
        <item isSort="false">
            <columnName>T_ORDER.EXT_CHK_5</columnName>
            <property>
                <key>property</key>
                <value>slipSearchByBuyerList[N].orderExtItem.extendChk.extendChk5</value>
            </property>
        </item>
        <item isSort="false">
            <columnName>T_ORDER.EXT_FILE_1</columnName>
            <property>
                <key>property</key>
                <value>slipSearchByBuyerList[N].orderExtItem.extendFile.extendFile1.fileName</value>
            </property>
        </item>
        <item isSort="false">
            <columnName>T_ORDER.EXT_FILE_2</columnName>
            <property>
                <key>property</key>
                <value>slipSearchByBuyerList[N].orderExtItem.extendFile.extendFile2.fileName</value>
            </property>
        </item>
        <item isSort="false">
            <columnName>T_ORDER.EXT_FILE_3</columnName>
            <property>
                <key>property</key>
                <value>slipSearchByBuyerList[N].orderExtItem.extendFile.extendFile3.fileName</value>
            </property>
        </item>
        <item isSort="false">
            <columnName>T_ORDER.EXT_FILE_BINARY_1</columnName>
            <property>
                <key>property</key>
                <value>slipSearchByBuyerList[N].orderExtItem.extendFile.extendFile1.binary</value>
            </property>
        </item>
        <item isSort="false">
            <columnName>T_ORDER.EXT_FILE_BINARY_2</columnName>
            <property>
                <key>property</key>
                <value>slipSearchByBuyerList[N].orderExtItem.extendFile.extendFile2.binary</value>
            </property>
        </item>
        <item isSort="false">
            <columnName>T_ORDER.EXT_FILE_BINARY_3</columnName>
            <property>
                <key>property</key>
                <value>slipSearchByBuyerList[N].orderExtItem.extendFile.extendFile3.binary</value>
            </property>
        </item>
        <item isSort="false">
            <columnName>T_ORDER.EXT_MST_1</columnName>
            <property>
                <key>masterCd</key>
                <value>slipSearchByBuyerList[N].orderExtItem.extendMst.extendMst1.mstKey</value>
            </property>
            <property>
                <key>masterName</key>
                <value>slipSearchByBuyerList[N].orderExtItem.extendMst.extendMst1.mstName</value>
            </property>
        </item>
        <item isSort="false">
            <columnName>T_ORDER.EXT_MST_2</columnName>
            <property>
                <key>masterCd</key>
                <value>slipSearchByBuyerList[N].orderExtItem.extendMst.extendMst2.mstKey</value>
            </property>
            <property>
                <key>masterName</key>
                <value>slipSearchByBuyerList[N].orderExtItem.extendMst.extendMst2.mstName</value>
            </property>
        </item>
        <item isSort="false">
            <columnName>T_ORDER.EXT_MST_3</columnName>
            <property>
                <key>masterCd</key>
                <value>slipSearchByBuyerList[N].orderExtItem.extendMst.extendMst3.mstKey</value>
            </property>
            <property>
                <key>masterName</key>
                <value>slipSearchByBuyerList[N].orderExtItem.extendMst.extendMst3.mstName</value>
            </property>
        </item>
        <item isSort="false">
            <columnName>T_ORDER.EXT_MST_4</columnName>
            <property>
                <key>masterCd</key>
                <value>slipSearchByBuyerList[N].orderExtItem.extendMst.extendMst4.mstKey</value>
            </property>
            <property>
                <key>masterName</key>
                <value>slipSearchByBuyerList[N].orderExtItem.extendMst.extendMst4.mstName</value>
            </property>
        </item>
        <item isSort="false">
            <columnName>T_ORDER.EXT_MST_5</columnName>
            <property>
                <key>masterCd</key>
                <value>slipSearchByBuyerList[N].orderExtItem.extendMst.extendMst5.mstKey</value>
            </property>
            <property>
                <key>masterName</key>
                <value>slipSearchByBuyerList[N].orderExtItem.extendMst.extendMst5.mstName</value>
            </property>
        </item>
        <item isSort="false">
            <columnName>T_ORDER.EXT_MST_6</columnName>
            <property>
                <key>masterCd</key>
                <value>slipSearchByBuyerList[N].orderExtItem.extendMst.extendMst6.mstKey</value>
            </property>
            <property>
                <key>masterName</key>
                <value>slipSearchByBuyerList[N].orderExtItem.extendMst.extendMst6.mstName</value>
            </property>
        </item>
        <item isSort="false">
            <columnName>T_ORDER.EXT_MST_7</columnName>
            <property>
                <key>masterCd</key>
                <value>slipSearchByBuyerList[N].orderExtItem.extendMst.extendMst7.mstKey</value>
            </property>
            <property>
                <key>masterName</key>
                <value>slipSearchByBuyerList[N].orderExtItem.extendMst.extendMst7.mstName</value>
            </property>
        </item>
        <item isSort="false">
            <columnName>T_ORDER.EXT_MST_8</columnName>
            <property>
                <key>masterCd</key>
                <value>slipSearchByBuyerList[N].orderExtItem.extendMst.extendMst8.mstKey</value>
            </property>
            <property>
                <key>masterName</key>
                <value>slipSearchByBuyerList[N].orderExtItem.extendMst.extendMst8.mstName</value>
            </property>
        </item>
        
    </area>
</itemSettingMapping>